pymcpautogui/__init__.py
pymcpautogui/server.py
pymcpautogui-0.1.1.dist-info/licenses/LICENSE
pymcpautogui-0.1.1.dist-info/METADATA
pymcpautogui-0.1.1.dist-info/WHEEL
pymcpautogui-0.1.1.dist-info/top_level.txt
pymcpautogui-0.1.1.dist-info/RECORD
